keystone_tempest_plugin/README.rst
keystone_tempest_plugin/__init__.py
keystone_tempest_plugin/clients.py
keystone_tempest_plugin/config.py
keystone_tempest_plugin/plugin.py
keystone_tempest_plugin/services/__init__.py
keystone_tempest_plugin/services/identity/__init__.py
keystone_tempest_plugin/services/identity/clients.py
keystone_tempest_plugin/services/identity/v3/__init__.py
keystone_tempest_plugin/services/identity/v3/auth_client.py
keystone_tempest_plugin/services/identity/v3/identity_providers_client.py
keystone_tempest_plugin/services/identity/v3/limits_client.py
keystone_tempest_plugin/services/identity/v3/mapping_rules_client.py
keystone_tempest_plugin/services/identity/v3/saml2_client.py
keystone_tempest_plugin/services/identity/v3/service_providers_client.py
keystone_tempest_plugin/tests/__init__.py
keystone_tempest_plugin/tests/base.py
keystone_tempest_plugin/tests/api/__init__.py
keystone_tempest_plugin/tests/api/identity/__init__.py
keystone_tempest_plugin/tests/api/identity/v3/__init__.py
keystone_tempest_plugin/tests/api/identity/v3/fixtures.py
keystone_tempest_plugin/tests/api/identity/v3/test_identity_providers.py
keystone_tempest_plugin/tests/api/identity/v3/test_mapping_rules.py
keystone_tempest_plugin/tests/api/identity/v3/test_oauth1_tokens.py
keystone_tempest_plugin/tests/api/identity/v3/test_service_providers.py
keystone_tempest_plugin/tests/rbac/__init__.py
keystone_tempest_plugin/tests/rbac/v3/__init__.py
keystone_tempest_plugin/tests/rbac/v3/base.py
keystone_tempest_plugin/tests/rbac/v3/test_access_rule.py
keystone_tempest_plugin/tests/rbac/v3/test_application_credential.py
keystone_tempest_plugin/tests/rbac/v3/test_consumer.py
keystone_tempest_plugin/tests/rbac/v3/test_credential.py
keystone_tempest_plugin/tests/rbac/v3/test_domain.py
keystone_tempest_plugin/tests/rbac/v3/test_domain_config.py
keystone_tempest_plugin/tests/rbac/v3/test_ec2_credential.py
keystone_tempest_plugin/tests/rbac/v3/test_endpoint.py
keystone_tempest_plugin-0.19.0.dist-info/AUTHORS
keystone_tempest_plugin-0.19.0.dist-info/LICENSE
keystone_tempest_plugin-0.19.0.dist-info/METADATA
keystone_tempest_plugin-0.19.0.dist-info/WHEEL
keystone_tempest_plugin-0.19.0.dist-info/entry_points.txt
keystone_tempest_plugin-0.19.0.dist-info/pbr.json
keystone_tempest_plugin-0.19.0.dist-info/top_level.txt
keystone_tempest_plugin-0.19.0.dist-info/RECORD
