Metadata-Version: 2.1
Name: keystone_tempest_plugin
Version: 0.19.0
Summary: Tempest plugin keystone_tempest_plugin
Home-page: https://docs.openstack.org/keystone/latest/
Author: OpenStack
Author-email: openstack-discuss@lists.openstack.org
Classifier: Environment :: OpenStack
Classifier: Intended Audience :: Information Technology
Classifier: Intended Audience :: System Administrators
Classifier: License :: OSI Approved :: Apache Software License
Classifier: Operating System :: POSIX :: Linux
Classifier: Programming Language :: Python
Classifier: Programming Language :: Python :: 3
Classifier: Programming Language :: Python :: 3.9
Classifier: Programming Language :: Python :: 3.10
Classifier: Programming Language :: Python :: 3.11
Classifier: Programming Language :: Python :: 3.12
Requires-Python: >=3.9
License-File: LICENSE
License-File: AUTHORS
Requires-Dist: pbr !=2.1.0,>=2.0.0
Requires-Dist: keystoneauth1 >=5.1.1
Requires-Dist: lxml !=3.7.0,>=3.4.1
Requires-Dist: tempest >=17.1.0
Requires-Dist: oslo.config >=5.2.0
Requires-Dist: testtools >=2.2.0
Requires-Dist: requests >=2.14.2
